gmsPython/__init__.py
gmsPython/auxfuncs.py
gmsPython/gamY/__init__.py
gmsPython/gamY/classes.py
gmsPython/gamY/gamY.py
gmsPython/gamY/patterns.py
gmsPython/gmsPy/__init__.py
gmsPython/gmsPy/gmsPy.py
gmsPython/gmsPyModels/__init__.py
gmsPython/gmsPyModels/gmsPyModels.py
gmsPython/gmsWrite/__init__.py
gmsPython/gmsWrite/gmsWrite.py
gmsPython/nestingTree/__init__.py
gmsPython/nestingTree/nestingTree.py
gmspython-0.1.13.dist-info/licenses/LICENSE
gmspython-0.1.13.dist-info/METADATA
gmspython-0.1.13.dist-info/WHEEL
gmspython-0.1.13.dist-info/top_level.txt
gmspython-0.1.13.dist-info/RECORD
