Metadata-Version: 2.4
Name: gmsPython
Version: 0.1.13
Summary: Automating GAMS models and execution from Python
Home-page: https://github.com/ChampionApe/gmsPython
Author: Rasmus K. Skjødt Berg
Author-email: rasmus.kehlet.berg@econ.ku.dk
Classifier: Programming Language :: Python :: 3
Classifier: License :: OSI Approved :: MIT License
Requires-Python: >=3.10
License-File: LICENSE
Requires-Dist: pandas
Requires-Dist: scipy
Requires-Dist: openpyxl
Requires-Dist: pyDatabases
Requires-Dist: gamsapi
Dynamic: author
Dynamic: author-email
Dynamic: classifier
Dynamic: description
Dynamic: description-content-type
Dynamic: home-page
Dynamic: license-file
Dynamic: requires-dist
Dynamic: requires-python
Dynamic: summary
